eagleview/__init__.py
eagleview/figshow.py
eagleview-1.1.dist-info/METADATA
eagleview-1.1.dist-info/WHEEL
eagleview-1.1.dist-info/top_level.txt
eagleview-1.1.dist-info/RECORD
