Metadata-Version: 2.1
Name: eagleview
Version: 1.1
Summary: Easy Visualisation of Plots
Home-page: https://github.com/hexronuspi/eagle/
Author: Aditya
Requires-Dist: matplotlib
Requires-Dist: Pillow
Requires-Dist: pandas
